gold33423302/__init__.py
gold33423302/gyat.py
gold33423302-0.0.1.dist-info/METADATA
gold33423302-0.0.1.dist-info/WHEEL
gold33423302-0.0.1.dist-info/top_level.txt
gold33423302-0.0.1.dist-info/RECORD
