Metadata-Version: 2.1
Name: gold33423302
Version: 0.0.1
Summary: Bruh calculate golden ratio
Home-page: 
Author: 
Author-email: 
License: MIT
Keywords: golden_ratio,golden
Platform: UNKNOWN
Classifier: Development Status :: 1 - Planning
